vgrepo/__init__.py
vgrepo/client.py
vgrepo/repository.py
vgrepo/settings.py
vgrepo/storage.py
vgrepo/usage.py
vgrepo/utils.py
vgrepo/meta/__init__.py
vgrepo/meta/base.py
vgrepo/meta/images.py
vgrepo-1.1.1.data/scripts/vgrepo
vgrepo-1.1.1.dist-info/DESCRIPTION.rst
vgrepo-1.1.1.dist-info/METADATA
vgrepo-1.1.1.dist-info/RECORD
vgrepo-1.1.1.dist-info/WHEEL
vgrepo-1.1.1.dist-info/metadata.json
vgrepo-1.1.1.dist-info/top_level.txt
