Metadata-Version: 2.0
Name: vgrepo
Version: 1.1.1
Summary: Utility for managing Vagrant repositories
Home-page: https://github.com/gongled/vgrepo
Author: Gleb Goncharov
Author-email: gongled@gongled.ru
License: MIT
Platform: Posix; MacOS X; Windows
Classifier: Development Status :: 5 - Production/Stable
Classifier: Intended Audience :: Developers
Classifier: Intended Audience :: System Administrators
Classifier: License :: OSI Approved :: MIT License
Classifier: Operating System :: OS Independent
Classifier: Programming Language :: Python :: 2
Classifier: Programming Language :: Python :: 2.7
Classifier: Programming Language :: Python :: 3
Classifier: Programming Language :: Python :: 3.4
Classifier: Programming Language :: Python
Classifier: Topic :: Software Development :: Libraries :: Python Modules
Requires-Dist: clint (>=0.5.0)
Requires-Dist: packaging
Requires-Dist: pyyaml
